nomad_camels_driver_zaber_x_rst240b_e08/zaber_x_rst240b_e08.py
nomad_camels_driver_zaber_x_rst240b_e08/zaber_x_rst240b_e08_ophyd.py
nomad_camels_driver_zaber_rst240b_e08-0.1.0.dist-info/LICENSE.txt
nomad_camels_driver_zaber_rst240b_e08-0.1.0.dist-info/METADATA
nomad_camels_driver_zaber_rst240b_e08-0.1.0.dist-info/WHEEL
nomad_camels_driver_zaber_rst240b_e08-0.1.0.dist-info/top_level.txt
nomad_camels_driver_zaber_rst240b_e08-0.1.0.dist-info/RECORD
